{
  "config": {
    "configFile": "D:\\Programming\\Playwright\\KiwiBank-Web\\playwright.config.js",
    "rootDir": "D:/Programming/Playwright/KiwiBank-Web/tests",
    "forbidOnly": false,
    "fullyParallel": true,
    "globalSetup": null,
    "globalTeardown": null,
    "globalTimeout": 0,
    "grep": {},
    "grepInvert": null,
    "maxFailures": 0,
    "metadata": {
      "actualWorkers": 8
    },
    "preserveOutput": "always",
    "reporter": [
      [
        "html",
        null
      ],
      [
        "junit",
        {
          "outputFile": "results.xml"
        }
      ],
      [
        "json",
        {
          "outputFile": "results.json"
        }
      ],
      [
        "D:\\Programming\\Playwright\\KiwiBank-Web\\node_modules\\allure-playwright\\dist\\index.js",
        {
          "outputFolder": "allure-results"
        }
      ]
    ],
    "reportSlowTests": {
      "max": 5,
      "threshold": 15000
    },
    "quiet": false,
    "projects": [
      {
        "outputDir": "D:/Programming/Playwright/KiwiBank-Web/test-results",
        "repeatEach": 1,
        "retries": 0,
        "id": "chromium",
        "name": "chromium",
        "testDir": "D:/Programming/Playwright/KiwiBank-Web/tests",
        "testIgnore": [],
        "testMatch": [
          "**/*.@(spec|test).?(c|m)[jt]s?(x)"
        ],
        "timeout": 30000
      }
    ],
    "shard": null,
    "updateSnapshots": "missing",
    "version": "1.42.1",
    "workers": 8,
    "webServer": null
  },
  "suites": [
    {
      "title": "API\\RequestInGET.spec.js",
      "file": "API/RequestInGET.spec.js",
      "column": 0,
      "line": 0,
      "specs": [
        {
          "title": "retrive ser list (GET REQUEST)",
          "ok": true,
          "tags": [],
          "tests": [
            {
              "timeout": 30000,
              "annotations": [],
              "expectedStatus": "passed",
              "projectId": "chromium",
              "projectName": "chromium",
              "results": [
                {
                  "workerIndex": 0,
                  "status": "passed",
                  "duration": 435,
                  "errors": [],
                  "stdout": [
                    {
                      "text": "status code-->200\n"
                    },
                    {
                      "text": "{\n  page: \u001b[33m2\u001b[39m,\n  per_page: \u001b[33m6\u001b[39m,\n  total: \u001b[33m12\u001b[39m,\n  total_pages: \u001b[33m2\u001b[39m,\n  data: [\n    {\n      id: \u001b[33m7\u001b[39m,\n      email: \u001b[32m'michael.lawson@reqres.in'\u001b[39m,\n      first_name: \u001b[32m'Michael'\u001b[39m,\n      last_name: \u001b[32m'Lawson'\u001b[39m,\n      avatar: \u001b[32m'https://reqres.in/img/faces/7-image.jpg'\u001b[39m\n    },\n    {\n      id: \u001b[33m8\u001b[39m,\n      email: \u001b[32m'lindsay.ferguson@reqres.in'\u001b[39m,\n      first_name: \u001b[32m'Lindsay'\u001b[39m,\n      last_name: \u001b[32m'Ferguson'\u001b[39m,\n      avatar: \u001b[32m'https://reqres.in/img/faces/8-image.jpg'\u001b[39m\n    },\n    {\n      id: \u001b[33m9\u001b[39m,\n      email: \u001b[32m'tobias.funke@reqres.in'\u001b[39m,\n      first_name: \u001b[32m'Tobias'\u001b[39m,\n      last_name: \u001b[32m'Funke'\u001b[39m,\n      avatar: \u001b[32m'https://reqres.in/img/faces/9-image.jpg'\u001b[39m\n    },\n    {\n      id: \u001b[33m10\u001b[39m,\n      email: \u001b[32m'byron.fields@reqres.in'\u001b[39m,\n      first_name: \u001b[32m'Byron'\u001b[39m,\n      last_name: \u001b[32m'Fields'\u001b[39m,\n      avatar: \u001b[32m'https://reqres.in/img/faces/10-image.jpg'\u001b[39m\n    },\n    {\n      id: \u001b[33m11\u001b[39m,\n      email: \u001b[32m'george.edwards@reqres.in'\u001b[39m,\n      first_name: \u001b[32m'George'\u001b[39m,\n      last_name: \u001b[32m'Edwards'\u001b[39m,\n      avatar: \u001b[32m'https://reqres.in/img/faces/11-image.jpg'\u001b[39m\n    },\n    {\n      id: \u001b[33m12\u001b[39m,\n      email: \u001b[32m'rachel.howell@reqres.in'\u001b[39m,\n      first_name: \u001b[32m'Rachel'\u001b[39m,\n      last_name: \u001b[32m'Howell'\u001b[39m,\n      avatar: \u001b[32m'https://reqres.in/img/faces/12-image.jpg'\u001b[39m\n    }\n  ],\n  support: {\n    url: \u001b[32m'https://reqres.in/#support-heading'\u001b[39m,\n    text: \u001b[32m'To keep ReqRes free, contributions towards server costs are appreciated!'\u001b[39m\n  }\n}\n"
                    }
                  ],
                  "stderr": [],
                  "retry": 0,
                  "startTime": "2024-03-20T03:35:52.084Z",
                  "attachments": []
                }
              ],
              "status": "expected"
            }
          ],
          "id": "6f571de52a0bf0318df1-f8d3f6cb945fef1275e9",
          "file": "API/RequestInGET.spec.js",
          "line": 3,
          "column": 5
        }
      ]
    },
    {
      "title": "API\\RequestInPOST.spec.js",
      "file": "API/RequestInPOST.spec.js",
      "column": 0,
      "line": 0,
      "specs": [
        {
          "title": "Create a user",
          "ok": true,
          "tags": [],
          "tests": [
            {
              "timeout": 30000,
              "annotations": [],
              "expectedStatus": "passed",
              "projectId": "chromium",
              "projectName": "chromium",
              "results": [
                {
                  "workerIndex": 1,
                  "status": "passed",
                  "duration": 893,
                  "errors": [],
                  "stdout": [],
                  "stderr": [],
                  "retry": 0,
                  "startTime": "2024-03-20T03:35:52.122Z",
                  "attachments": []
                }
              ],
              "status": "expected"
            }
          ],
          "id": "895683d90a892a882df4-caedce5c93df3becdfbf",
          "file": "API/RequestInPOST.spec.js",
          "line": 3,
          "column": 5
        }
      ]
    },
    {
      "title": "API\\RequestInPUT.spec.js",
      "file": "API/RequestInPUT.spec.js",
      "column": 0,
      "line": 0,
      "specs": [
        {
          "title": "update user",
          "ok": true,
          "tags": [],
          "tests": [
            {
              "timeout": 30000,
              "annotations": [],
              "expectedStatus": "passed",
              "projectId": "chromium",
              "projectName": "chromium",
              "results": [
                {
                  "workerIndex": 2,
                  "status": "passed",
                  "duration": 856,
                  "errors": [],
                  "stdout": [],
                  "stderr": [],
                  "retry": 0,
                  "startTime": "2024-03-20T03:35:52.133Z",
                  "attachments": []
                }
              ],
              "status": "expected"
            }
          ],
          "id": "e42d8499ad0b118a2f81-11a0ef8ddb8882b6677c",
          "file": "API/RequestInPUT.spec.js",
          "line": 3,
          "column": 1
        }
      ]
    },
    {
      "title": "UI\\BusinessPage.spec.js",
      "file": "UI/BusinessPage.spec.js",
      "column": 0,
      "line": 0,
      "specs": [
        {
          "title": "validate Business special table",
          "ok": true,
          "tags": [],
          "tests": [
            {
              "timeout": 30000,
              "annotations": [],
              "expectedStatus": "passed",
              "projectId": "chromium",
              "projectName": "chromium",
              "results": [
                {
                  "workerIndex": 3,
                  "status": "passed",
                  "duration": 10922,
                  "errors": [],
                  "stdout": [],
                  "stderr": [],
                  "retry": 0,
                  "startTime": "2024-03-20T03:35:52.090Z",
                  "attachments": []
                }
              ],
              "status": "expected"
            }
          ],
          "id": "49b4101c0381c2eea7ec-4a50d011ea08bee119ce",
          "file": "UI/BusinessPage.spec.js",
          "line": 17,
          "column": 5
        },
        {
          "title": "Validate Card type",
          "ok": true,
          "tags": [],
          "tests": [
            {
              "timeout": 30000,
              "annotations": [],
              "expectedStatus": "passed",
              "projectId": "chromium",
              "projectName": "chromium",
              "results": [
                {
                  "workerIndex": 4,
                  "status": "passed",
                  "duration": 11598,
                  "errors": [],
                  "stdout": [],
                  "stderr": [],
                  "retry": 0,
                  "startTime": "2024-03-20T03:35:52.144Z",
                  "attachments": []
                }
              ],
              "status": "expected"
            }
          ],
          "id": "49b4101c0381c2eea7ec-99578a37332052bdf00e",
          "file": "UI/BusinessPage.spec.js",
          "line": 24,
          "column": 5
        },
        {
          "title": "Validate Rate",
          "ok": true,
          "tags": [],
          "tests": [
            {
              "timeout": 30000,
              "annotations": [],
              "expectedStatus": "passed",
              "projectId": "chromium",
              "projectName": "chromium",
              "results": [
                {
                  "workerIndex": 5,
                  "status": "passed",
                  "duration": 11645,
                  "errors": [],
                  "stdout": [
                    {
                      "text": "--rate --: Term Deposit (1 year)\n"
                    }
                  ],
                  "stderr": [],
                  "retry": 0,
                  "startTime": "2024-03-20T03:35:52.162Z",
                  "attachments": []
                }
              ],
              "status": "expected"
            }
          ],
          "id": "49b4101c0381c2eea7ec-73107b88a586a522e0cc",
          "file": "UI/BusinessPage.spec.js",
          "line": 31,
          "column": 5
        },
        {
          "title": "Validate Sub Heading",
          "ok": true,
          "tags": [],
          "tests": [
            {
              "timeout": 30000,
              "annotations": [],
              "expectedStatus": "passed",
              "projectId": "chromium",
              "projectName": "chromium",
              "results": [
                {
                  "workerIndex": 6,
                  "status": "passed",
                  "duration": 11881,
                  "errors": [],
                  "stdout": [
                    {
                      "text": "--rate --: Fixed returns on money locked in for a set period.\n"
                    }
                  ],
                  "stderr": [],
                  "retry": 0,
                  "startTime": "2024-03-20T03:35:52.156Z",
                  "attachments": []
                }
              ],
              "status": "expected"
            }
          ],
          "id": "49b4101c0381c2eea7ec-732ab61201b220ae817b",
          "file": "UI/BusinessPage.spec.js",
          "line": 37,
          "column": 5
        }
      ]
    },
    {
      "title": "UI\\HomePage.spec.js",
      "file": "UI/HomePage.spec.js",
      "column": 0,
      "line": 0,
      "specs": [],
      "suites": [
        {
          "title": "Home Page UI testing",
          "file": "UI/HomePage.spec.js",
          "line": 4,
          "column": 6,
          "specs": [
            {
              "title": "Validate home Page Title",
              "ok": true,
              "tags": [],
              "tests": [
                {
                  "timeout": 30000,
                  "annotations": [],
                  "expectedStatus": "passed",
                  "projectId": "chromium",
                  "projectName": "chromium",
                  "results": [
                    {
                      "workerIndex": 7,
                      "status": "passed",
                      "duration": 3941,
                      "errors": [],
                      "stdout": [],
                      "stderr": [],
                      "retry": 0,
                      "startTime": "2024-03-20T03:35:52.119Z",
                      "attachments": []
                    }
                  ],
                  "status": "expected"
                }
              ],
              "id": "eb41ccff382dfbf64f22-2d2e974040f42126fa97",
              "file": "UI/HomePage.spec.js",
              "line": 9,
              "column": 5
            },
            {
              "title": "verify landing url",
              "ok": true,
              "tags": [],
              "tests": [
                {
                  "timeout": 30000,
                  "annotations": [],
                  "expectedStatus": "passed",
                  "projectId": "chromium",
                  "projectName": "chromium",
                  "results": [
                    {
                      "workerIndex": 0,
                      "status": "passed",
                      "duration": 4337,
                      "errors": [],
                      "stdout": [],
                      "stderr": [],
                      "retry": 0,
                      "startTime": "2024-03-20T03:35:52.543Z",
                      "attachments": []
                    }
                  ],
                  "status": "expected"
                }
              ],
              "id": "eb41ccff382dfbf64f22-125b5819dda97cb881e7",
              "file": "UI/HomePage.spec.js",
              "line": 13,
              "column": 5
            },
            {
              "title": "Validate Personal category in the home page",
              "ok": true,
              "tags": [],
              "tests": [
                {
                  "timeout": 30000,
                  "annotations": [],
                  "expectedStatus": "passed",
                  "projectId": "chromium",
                  "projectName": "chromium",
                  "results": [
                    {
                      "workerIndex": 2,
                      "status": "passed",
                      "duration": 4414,
                      "errors": [],
                      "stdout": [],
                      "stderr": [],
                      "retry": 0,
                      "startTime": "2024-03-20T03:35:53.011Z",
                      "attachments": []
                    }
                  ],
                  "status": "expected"
                }
              ],
              "id": "eb41ccff382dfbf64f22-081ea80ca22f10e1d80b",
              "file": "UI/HomePage.spec.js",
              "line": 18,
              "column": 5
            }
          ]
        }
      ]
    },
    {
      "title": "UI\\PersonalPage.spec.js",
      "file": "UI/PersonalPage.spec.js",
      "column": 0,
      "line": 0,
      "specs": [
        {
          "title": "validate Personal special rate data",
          "ok": true,
          "tags": [],
          "tests": [
            {
              "timeout": 0,
              "annotations": [],
              "expectedStatus": "passed",
              "projectId": "chromium",
              "projectName": "chromium",
              "results": [
                {
                  "workerIndex": 1,
                  "status": "passed",
                  "duration": 6827,
                  "errors": [],
                  "stdout": [],
                  "stderr": [],
                  "retry": 0,
                  "startTime": "2024-03-20T03:35:53.040Z",
                  "attachments": []
                }
              ],
              "status": "expected"
            }
          ],
          "id": "2683e441702f5e6a9c8e-9aa348e3d8ee1cfbb76e",
          "file": "UI/PersonalPage.spec.js",
          "line": 16,
          "column": 5
        },
        {
          "title": "Validate Card type",
          "ok": true,
          "tags": [],
          "tests": [
            {
              "timeout": 30000,
              "annotations": [],
              "expectedStatus": "passed",
              "projectId": "chromium",
              "projectName": "chromium",
              "results": [
                {
                  "workerIndex": 7,
                  "status": "passed",
                  "duration": 6043,
                  "errors": [],
                  "stdout": [],
                  "stderr": [],
                  "retry": 0,
                  "startTime": "2024-03-20T03:35:56.330Z",
                  "attachments": []
                }
              ],
              "status": "expected"
            }
          ],
          "id": "2683e441702f5e6a9c8e-b7ab5d21b50855bf4dfc",
          "file": "UI/PersonalPage.spec.js",
          "line": 24,
          "column": 5
        },
        {
          "title": "Validate Rate",
          "ok": true,
          "tags": [],
          "tests": [
            {
              "timeout": 30000,
              "annotations": [],
              "expectedStatus": "passed",
              "projectId": "chromium",
              "projectName": "chromium",
              "results": [
                {
                  "workerIndex": 0,
                  "status": "passed",
                  "duration": 6256,
                  "errors": [],
                  "stdout": [
                    {
                      "text": "--rate --: 6.79%p.a.\n"
                    }
                  ],
                  "stderr": [],
                  "retry": 0,
                  "startTime": "2024-03-20T03:35:57.293Z",
                  "attachments": []
                }
              ],
              "status": "expected"
            }
          ],
          "id": "2683e441702f5e6a9c8e-ff73b24423ee586738a9",
          "file": "UI/PersonalPage.spec.js",
          "line": 32,
          "column": 5
        },
        {
          "title": "Validate Sub Heading",
          "ok": true,
          "tags": [],
          "tests": [
            {
              "timeout": 30000,
              "annotations": [],
              "expectedStatus": "passed",
              "projectId": "chromium",
              "projectName": "chromium",
              "results": [
                {
                  "workerIndex": 2,
                  "status": "passed",
                  "duration": 6408,
                  "errors": [],
                  "stdout": [
                    {
                      "text": "--rate --: 2 years fixed\n"
                    }
                  ],
                  "stderr": [],
                  "retry": 0,
                  "startTime": "2024-03-20T03:35:57.827Z",
                  "attachments": []
                }
              ],
              "status": "expected"
            }
          ],
          "id": "2683e441702f5e6a9c8e-7b86b890f4641a6f6184",
          "file": "UI/PersonalPage.spec.js",
          "line": 39,
          "column": 5
        },
        {
          "title": "Validate Terms",
          "ok": true,
          "tags": [],
          "tests": [
            {
              "timeout": 30000,
              "annotations": [],
              "expectedStatus": "passed",
              "projectId": "chromium",
              "projectName": "chromium",
              "results": [
                {
                  "workerIndex": 1,
                  "status": "passed",
                  "duration": 5060,
                  "errors": [],
                  "stdout": [
                    {
                      "text": "--rate --: 2 years fixed. Min 20% equity.\n"
                    }
                  ],
                  "stderr": [],
                  "retry": 0,
                  "startTime": "2024-03-20T03:36:00.370Z",
                  "attachments": []
                }
              ],
              "status": "expected"
            }
          ],
          "id": "2683e441702f5e6a9c8e-6b8755979843845459e0",
          "file": "UI/PersonalPage.spec.js",
          "line": 46,
          "column": 5
        }
      ]
    }
  ],
  "errors": [],
  "stats": {
    "startTime": "2024-03-20T03:35:50.749Z",
    "duration": 14755.66,
    "expected": 15,
    "skipped": 0,
    "unexpected": 0,
    "flaky": 0
  }
}